{
  "userAdmonitions": {},
  "syntaxHighlight": false,
  "copyButton": true,
  "version": "10.3.2",
  "autoCollapse": true,
  "defaultCollapseType": "open",
  "injectColor": true,
  "parseTitles": true,
  "dropShadow": true,
  "hideEmpty": true,
  "open": {
    "admonitions": true,
    "icons": true,
    "other": true,
    "advanced": true
  },
  "icons": [],
  "useFontAwesome": true,
  "rpgDownloadedOnce": false,
  "msDocConverted": false,
  "useSnippet": false,
  "snippetPath": "custom-admonitions.aed7cc"
}